panphylo/__init__.py
panphylo/__main__.py
panphylo/common.py
panphylo/common_io.py
panphylo/nexus.py
panphylo/phylip.py
panphylo/phylodata.py
panphylo/tabular.py
panphylo-0.3.dist-info/AUTHORS.md
panphylo-0.3.dist-info/LICENSE
panphylo-0.3.dist-info/METADATA
panphylo-0.3.dist-info/WHEEL
panphylo-0.3.dist-info/entry_points.txt
panphylo-0.3.dist-info/top_level.txt
panphylo-0.3.dist-info/RECORD
