Metadata-Version: 2.1
Name: panphylo
Version: 0.3
Summary: A tool for converting and manipulating phylogenetic data
Home-page: https://github.com/tresoldi/panphylo
Author: Tiago Tresoldi
Author-email: tiago.tresoldi@lingfil.uu.se
License: MIT
Keywords: phylogenetics,nexus,phylip
Classifier: License :: OSI Approved :: MIT License
Classifier: Operating System :: OS Independent
Classifier: Programming Language :: Python :: 3
Classifier: Topic :: Software Development :: Libraries
Requires-Python: >=3.6
License-File: LICENSE
License-File: AUTHORS.md
Requires-Dist: chardet
Requires-Dist: unidecode
Provides-Extra: dev
Requires-Dist: black ; extra == 'dev'
Requires-Dist: flake8 ; extra == 'dev'
Requires-Dist: twine ; extra == 'dev'
Requires-Dist: wheel ; extra == 'dev'
Provides-Extra: test
Requires-Dist: pytest ; extra == 'test'
